jaraco/functools/__init__.py
jaraco/functools/__init__.pyi
jaraco/functools/py.typed
jaraco_functools-4.2.0.dist-info/licenses/LICENSE
jaraco_functools-4.2.0.dist-info/METADATA
jaraco_functools-4.2.0.dist-info/WHEEL
jaraco_functools-4.2.0.dist-info/top_level.txt
jaraco_functools-4.2.0.dist-info/RECORD
